formulaire_app/__init__.py
formulaire_app/admin.py
formulaire_app/apps.py
formulaire_app/cli.py
formulaire_app/forms.py
formulaire_app/generate.py
formulaire_app/models.py
formulaire_app/tests.py
formulaire_app/urls.py
formulaire_app/views.py
formulaire_app/migrations/0001_initial.py
formulaire_app/migrations/__init__.py
formulaire_app/static/formulaire_app/script.js
formulaire_app/static/formulaire_app/style.css
formulaire_app/templates/formulaire_app/forgot_password.html
formulaire_app/templates/formulaire_app/login.html
formulaire_app/templates/formulaire_app/register.html
formulaire_app-0.2.4.dist-info/licenses/LICENSE
formulaire_app-0.2.4.dist-info/METADATA
formulaire_app-0.2.4.dist-info/WHEEL
formulaire_app-0.2.4.dist-info/entry_points.txt
formulaire_app-0.2.4.dist-info/top_level.txt
formulaire_app-0.2.4.dist-info/RECORD
